LICENSE.txt
MANIFEST.in
README.rst
setup.py
excel_csv_helpers.egg-info/PKG-INFO
excel_csv_helpers.egg-info/SOURCES.txt
excel_csv_helpers.egg-info/dependency_links.txt
excel_csv_helpers.egg-info/top_level.txt
helpers/pythonLib.py
tests/__init__.py
tests/test_sample.py